vivarium_public_health/__about__.py
vivarium_public_health/__init__.py
vivarium_public_health/_version.py
vivarium_public_health/utilities.py
vivarium_public_health/disease/__init__.py
vivarium_public_health/disease/exceptions.py
vivarium_public_health/disease/model.py
vivarium_public_health/disease/models.py
vivarium_public_health/disease/special_disease.py
vivarium_public_health/disease/state.py
vivarium_public_health/disease/transition.py
vivarium_public_health/mslt/__init__.py
vivarium_public_health/mslt/delay.py
vivarium_public_health/mslt/disease.py
vivarium_public_health/mslt/intervention.py
vivarium_public_health/mslt/magic_wand_components.py
vivarium_public_health/mslt/observer.py
vivarium_public_health/mslt/population.py
vivarium_public_health/plugins/__init__.py
vivarium_public_health/plugins/parser.py
vivarium_public_health/population/__init__.py
vivarium_public_health/population/add_new_birth_cohorts.py
vivarium_public_health/population/base_population.py
vivarium_public_health/population/data_transformations.py
vivarium_public_health/population/mortality.py
vivarium_public_health/results/__init__.py
vivarium_public_health/results/columns.py
vivarium_public_health/results/disability.py
vivarium_public_health/results/disease.py
vivarium_public_health/results/mortality.py
vivarium_public_health/results/observer.py
vivarium_public_health/results/risk.py
vivarium_public_health/results/simple_cause.py
vivarium_public_health/results/stratification.py
vivarium_public_health/risks/__init__.py
vivarium_public_health/risks/base_risk.py
vivarium_public_health/risks/data_transformations.py
vivarium_public_health/risks/distributions.py
vivarium_public_health/risks/effect.py
vivarium_public_health/risks/implementations/__init__.py
vivarium_public_health/risks/implementations/low_birth_weight_and_short_gestation.py
vivarium_public_health/treatment/__init__.py
vivarium_public_health/treatment/magic_wand.py
vivarium_public_health/treatment/scale_up.py
vivarium_public_health-4.13.17.dist-info/licenses/LICENSE.txt
vivarium_public_health-4.13.17.dist-info/METADATA
vivarium_public_health-4.13.17.dist-info/WHEEL
vivarium_public_health-4.13.17.dist-info/top_level.txt
vivarium_public_health-4.13.17.dist-info/RECORD
